lokalise/__init__.py
lokalise/_version.py
lokalise/base_client.py
lokalise/client.py
lokalise/errors.py
lokalise/oauth_client.py
lokalise/request.py
lokalise/request_utils.py
lokalise/types.py
lokalise/utils.py
lokalise/client_methods/__init__.py
lokalise/client_methods/branches.py
lokalise/client_methods/comments.py
lokalise/client_methods/contributors.py
lokalise/client_methods/endpoint_provider.py
lokalise/client_methods/files.py
lokalise/client_methods/glossary_terms.py
lokalise/client_methods/jwt.py
lokalise/client_methods/keys.py
lokalise/client_methods/languages.py
lokalise/client_methods/orders.py
lokalise/client_methods/payment_cards.py
lokalise/client_methods/permission_templates.py
lokalise/client_methods/processes.py
lokalise/client_methods/projects.py
lokalise/client_methods/screenshots.py
lokalise/client_methods/segments.py
lokalise/client_methods/snapshots.py
lokalise/client_methods/tasks.py
lokalise/client_methods/team_user_billing_details.py
lokalise/client_methods/team_user_groups.py
lokalise/client_methods/team_users.py
lokalise/client_methods/teams.py
lokalise/client_methods/translation_providers.py
lokalise/client_methods/translation_statuses.py
lokalise/client_methods/translations.py
lokalise/client_methods/webhooks.py
lokalise/collections/__init__.py
lokalise/collections/base_collection.py
lokalise/collections/branches.py
lokalise/collections/comments.py
lokalise/collections/contributors.py
lokalise/collections/files.py
lokalise/collections/glossary_terms.py
lokalise/collections/keys.py
lokalise/collections/languages.py
lokalise/collections/orders.py
lokalise/collections/payment_cards.py
lokalise/collections/permission_templates.py
lokalise/collections/projects.py
lokalise/collections/queued_processes.py
lokalise/collections/screenshots.py
lokalise/collections/segments.py
lokalise/collections/snapshots.py
lokalise/collections/tasks.py
lokalise/collections/team_user_groups.py
lokalise/collections/team_users.py
lokalise/collections/teams.py
python_lokalise_api-4.0.1.dist-info/METADATA
python_lokalise_api-4.0.1.dist-info/WHEEL
python_lokalise_api-4.0.1.dist-info/licenses/LICENSE
python_lokalise_api-4.0.1.dist-info/RECORD
