Metadata-Version: 2.4
Name: python-lokalise-api
Version: 4.0.1
Summary: Official Python interface for the Lokalise API v2
Project-URL: Homepage, https://python-lokalise-api.readthedocs.io/
Project-URL: Repository, https://github.com/lokalise/python-lokalise-api
Project-URL: Issues, https://github.com/lokalise/python-lokalise-api/issues
Project-URL: Documentation, https://python-lokalise-api.readthedocs.io/
Author-email: Ilya Krukowski <elskruk@proton.me>
License-File: LICENSE
Keywords: api,client,lokalise
Classifier: Development Status :: 5 - Production/Stable
Classifier: Intended Audience :: Developers
Classifier: License :: OSI Approved :: BSD License
Classifier: Operating System :: OS Independent
Classifier: Programming Language :: Python :: 3
Classifier: Topic :: Software Development :: Libraries :: Python Modules
Requires-Python: >=3.10
Requires-Dist: exceptiongroup<2.0,>=1.0; python_version < '3.11'
Requires-Dist: requests<3,>=2.32.5
